[
    {
      "bookId": 1,
      "bookName": "The Dating Playbook for Men",
      "author": "Andrew Ferebee",
      "image": "https://i.ibb.co/hMMgdCd/book1.png",
      "review": "A comprehensive guide for men navigating the complexities of dating, offering practical advice and strategies.",
      "totalPages": 278,
      "rating": 4.6,
      "category": "Relationships",
      "tags": ["Dating", "Self-Help", "Communication"],
      "publisher": "Knowledge for Men",
      "yearOfPublishing": 2015
    },
    {
      "bookId": 2,
      "bookName": "Why Do You Hate Money?",
      "author": "Bailey Richert",
      "image": "https://i.ibb.co/7NGqgNS/book2.png",
      "review": "An insightful exploration of mindset and beliefs surrounding money, empowering readers to overcome financial obstacles.",
      "totalPages": 210,
      "rating": 4.3,
      "category": "Personal Finance",
      "tags": ["Money Management", "Wealth Mindset"],
      "publisher": "Bailey Richert",
      "yearOfPublishing": 2018
    },
    {
      "bookId": 3,
      "bookName": "The Hate U Give",
      "author": "Angie Thomas",
      "image": "https://i.ibb.co/zHrFb1y/book3.png",
      "review": "A powerful and timely novel shedding light on racial injustice and the importance of finding one's voice in the face of adversity.",
      "totalPages": 444,
      "rating": 4.7,
      "category": "Young Adult Fiction",
      "tags": ["Social Justice", "Coming of Age"],
      "publisher": "Balzer + Bray",
      "yearOfPublishing": 2017
    },
    {
      "bookId": 4,
      "bookName": "Scholarship Monthly Planner",
      "author": "Marianne Ragins",
      "image": "https://i.ibb.co/7GkV9F2/book4.png",
      "review": "A helpful tool for organizing scholarship deadlines and application requirements, aiding students in their pursuit of higher education funding.",
      "totalPages": 128,
      "rating": 4.0,
      "category": "Education",
      "tags": ["Scholarships", "Planning", "Education"],
      "publisher": "Unknown",
      "yearOfPublishing": 2021
    },
    {
      "bookId": 5,
      "bookName": "Annotated Texas Family Code 2019",
      "author": "West's Texas Statutes and Codes",
      "image": "https://i.ibb.co/7bwhS7m/book5.png",
      "review": "A comprehensive reference guide providing annotations and interpretations of the Texas Family Code for legal practitioners.",
      "totalPages": 1200,
      "rating": 4.5,
      "category": "Law",
      "tags": ["Legal Reference", "Texas Law"],
      "publisher": "Thomson Reuters",
      "yearOfPublishing": 2019
    },
    {
      "bookId": 6,
      "bookName": "Loving Jesus More",
      "author": "Phil Ryken",
      "image": "https://i.ibb.co/LQXfvqN/book6.png",
      "review": "A spiritual journey towards deepening one's relationship with Jesus Christ, offering insights and reflections on faith.",
      "totalPages": 176,
      "rating": 4.8,
      "category": "Christian Living",
      "tags": ["Faith", "Spirituality", "Christianity"],
      "publisher": "Crossway",
      "yearOfPublishing": 2005
    },
    {
      "bookId": 7,
      "bookName": "The Lost Art of Conversation",
      "author": "Sari Solden",
      "image": "https://i.ibb.co/kSWcYdt/book7.png",
      "review": "A guide to revitalizing meaningful communication in a digital age, emphasizing empathy and active listening.",
      "totalPages": 256,
      "rating": 4.4,
      "category": "Self-Help",
      "tags": ["Communication Skills", "Empathy"],
      "publisher": "Walker & Company",
      "yearOfPublishing": 2000
    },
    {
      "bookId": 8,
      "bookName": "Cold-Case Christianity",
      "author": "J. Warner Wallace",
      "image": "https://i.ibb.co/R0pFzRP/book8.png",
      "review": "A detective's approach to examining the reliability of the New Testament, providing evidence for the truth of Christianity.",
      "totalPages": 288,
      "rating": 4.6,
      "category": "Religion",
      "tags": ["Christian Apologetics", "Evidence"],
      "publisher": "David C. Cook",
      "yearOfPublishing": 2013
    },
    {
      "bookId": 9,
      "bookName": "Spine of the Dragon",
      "author": "Kevin J. Anderson",
      "image": "https://i.ibb.co/CP1R9LH/book9.png",
      "review": "An epic fantasy adventure set in a world of dragons, magic, and political intrigue, captivating readers with its rich storytelling.",
      "totalPages": 560,
      "rating": 4.7,
      "category": "Fantasy Fiction",
      "tags": ["Epic Fantasy", "Magic", "Dragons"],
      "publisher": "Tor Books",
      "yearOfPublishing": 2018
    }
  ]
  